MANIFEST.in
README.md
VERSION
setup.py
cSecp256k1/__init__.py
cSecp256k1.egg-info/PKG-INFO
cSecp256k1.egg-info/SOURCES.txt
cSecp256k1.egg-info/dependency_links.txt
cSecp256k1.egg-info/top_level.txt
src/ecdsa.c
src/ecdsa.h
src/schnorr.c
src/schnorr.h
src/secp256k1.h
src/sha256.c
src/sha256.h
test/test_code.py
test/test_signatures.py
test/test_vectors.py